[
    {
        "Title": "Psalms:141:1",
        "Content": "JEHOVA, á ti he clamado; apresúrate á mí; Escucha mi voz, cuando te invocare.",
        "Url": "https://wol.jw.org/es/wol/binav/r4/lp-s/nwtsty"
    },
    {
        "Title": "Psalms:141:2",
        "Content": "Sea enderezada mi oración delante de ti como un perfume, El don de mis manos como la ofrenda de la tarde.",
        "Url": "https://wol.jw.org/es/wol/binav/r4/lp-s/nwtsty"
    },
    {
        "Title": "Psalms:141:3",
        "Content": "Pon, oh Jehová, guarda á mi boca: Guarda la puerta de mis labios.",
        "Url": "https://wol.jw.org/es/wol/binav/r4/lp-s/nwtsty"
    },
    {
        "Title": "Psalms:141:4",
        "Content": "No dejes se incline mi corazón á cosa mala, A hacer obras impías Con los que obran iniquidad, Y no coma yo de sus deleites.",
        "Url": "https://wol.jw.org/es/wol/binav/r4/lp-s/nwtsty"
    },
    {
        "Title": "Psalms:141:5",
        "Content": "Que el justo me castigue, será un favor, Y que me reprenda será un excelente bálsamo. Que no me herirá la cabeza: Así que aun mi oración tendrán en sus calamidades.",
        "Url": "https://wol.jw.org/es/wol/binav/r4/lp-s/nwtsty"
    },
    {
        "Title": "Psalms:141:6",
        "Content": "Serán derribados en lugares peñascosos sus jueces, Y oirán mis palabras, que son suaves.",
        "Url": "https://wol.jw.org/es/wol/binav/r4/lp-s/nwtsty"
    },
    {
        "Title": "Psalms:141:7",
        "Content": "Como quien hiende y rompe la tierra, Son esparcidos nuestros huesos á la boca de la sepultura.",
        "Url": "https://wol.jw.org/es/wol/binav/r4/lp-s/nwtsty"
    },
    {
        "Title": "Psalms:141:8",
        "Content": "Por tanto á ti, oh Jehová Señor, miran mis ojos: En ti he confiado, no desampares mi alma.",
        "Url": "https://wol.jw.org/es/wol/binav/r4/lp-s/nwtsty"
    },
    {
        "Title": "Psalms:141:9",
        "Content": "Guárdame de los lazos que me han tendido, Y de los armadijos de los que obran iniquidad.",
        "Url": "https://wol.jw.org/es/wol/binav/r4/lp-s/nwtsty"
    },
    {
        "Title": "Psalms:141:10",
        "Content": "Caigan los impíos á una en sus redes, Mientras yo pasaré adelante.",
        "Url": "https://wol.jw.org/es/wol/binav/r4/lp-s/nwtsty"
    }
]