[
    {
        "Title": "Psalms:72:1",
        "Content": "OH Dios, da tus juicios al rey, Y tu justicia al hijo del rey.",
        "Url": "https://wol.jw.org/es/wol/binav/r4/lp-s/nwtsty"
    },
    {
        "Title": "Psalms:72:2",
        "Content": "El juzgará tu pueblo con justicia, Y tus afligidos con juicio.",
        "Url": "https://wol.jw.org/es/wol/binav/r4/lp-s/nwtsty"
    },
    {
        "Title": "Psalms:72:3",
        "Content": "Los montes llevarán paz al pueblo, Y los collados justicia.",
        "Url": "https://wol.jw.org/es/wol/binav/r4/lp-s/nwtsty"
    },
    {
        "Title": "Psalms:72:4",
        "Content": "Juzgará los afligidos del pueblo, Salvará los hijos del menesteroso, Y quebrantará al violento.",
        "Url": "https://wol.jw.org/es/wol/binav/r4/lp-s/nwtsty"
    },
    {
        "Title": "Psalms:72:5",
        "Content": "Temerte han mientras duren el sol Y la luna, por generación de generaciones.",
        "Url": "https://wol.jw.org/es/wol/binav/r4/lp-s/nwtsty"
    },
    {
        "Title": "Psalms:72:6",
        "Content": "Descenderá como la lluvia sobre la hierba cortada; Como el rocío que destila sobre la tierra.",
        "Url": "https://wol.jw.org/es/wol/binav/r4/lp-s/nwtsty"
    },
    {
        "Title": "Psalms:72:7",
        "Content": "Florecerá en sus día justicia, Y muchedumbre de paz, hasta que no haya luna.",
        "Url": "https://wol.jw.org/es/wol/binav/r4/lp-s/nwtsty"
    },
    {
        "Title": "Psalms:72:8",
        "Content": "Y dominará de mar á mar, Y desde el río hasta los cabos de la tierra.",
        "Url": "https://wol.jw.org/es/wol/binav/r4/lp-s/nwtsty"
    },
    {
        "Title": "Psalms:72:9",
        "Content": "Delante de él se postrarán los Etiopes; Y sus enemigos lamerán la tierra.",
        "Url": "https://wol.jw.org/es/wol/binav/r4/lp-s/nwtsty"
    },
    {
        "Title": "Psalms:72:10",
        "Content": "Los reyes de Tharsis y de las islas traerán presentes: Los reyes de Sheba y de Seba ofrecerán dones.",
        "Url": "https://wol.jw.org/es/wol/binav/r4/lp-s/nwtsty"
    },
    {
        "Title": "Psalms:72:11",
        "Content": "Y arrodillarse han á él todos los reyes; Le servirán todas las gentes.",
        "Url": "https://wol.jw.org/es/wol/binav/r4/lp-s/nwtsty"
    },
    {
        "Title": "Psalms:72:12",
        "Content": "Porque él librará al menesteroso que clamare, Y al afligido que no tuviere quien le socorra.",
        "Url": "https://wol.jw.org/es/wol/binav/r4/lp-s/nwtsty"
    },
    {
        "Title": "Psalms:72:13",
        "Content": "Tendrá misericordia del pobre y del menesteroso, Y salvará las almas de los pobres.",
        "Url": "https://wol.jw.org/es/wol/binav/r4/lp-s/nwtsty"
    },
    {
        "Title": "Psalms:72:14",
        "Content": "De engaño y de violencia redimirá sus almas: Y la sangre de ellos será preciosa en sus ojos.",
        "Url": "https://wol.jw.org/es/wol/binav/r4/lp-s/nwtsty"
    },
    {
        "Title": "Psalms:72:15",
        "Content": "Y vivirá, y darásele del oro de Seba; Y oraráse por él continuamente; Todo el día se le bendecirá.",
        "Url": "https://wol.jw.org/es/wol/binav/r4/lp-s/nwtsty"
    },
    {
        "Title": "Psalms:72:16",
        "Content": "Será echado un puño de grano en tierra, en las cumbres de los montes; Su fruto hará ruido como el Líbano, Y los de la ciudad florecerán como la hierba de la tierra.",
        "Url": "https://wol.jw.org/es/wol/binav/r4/lp-s/nwtsty"
    },
    {
        "Title": "Psalms:72:17",
        "Content": "Será su nombre para siempre, Perpetuaráse su nombre mientras el sol dure: Y benditas serán en él todas las gentes: Llamarlo han bienaventurado.",
        "Url": "https://wol.jw.org/es/wol/binav/r4/lp-s/nwtsty"
    },
    {
        "Title": "Psalms:72:18",
        "Content": "Bendito Jehová Dios, el Dios de Israel, Que solo hace maravillas.",
        "Url": "https://wol.jw.org/es/wol/binav/r4/lp-s/nwtsty"
    },
    {
        "Title": "Psalms:72:19",
        "Content": "Y bendito su nombre glorioso para siempre: Y toda la tierra sea llena de su gloria. Amén y Amén.",
        "Url": "https://wol.jw.org/es/wol/binav/r4/lp-s/nwtsty"
    },
    {
        "Title": "Psalms:72:20",
        "Content": "Acábanse las oraciones de David, hijo de Isaí.",
        "Url": "https://wol.jw.org/es/wol/binav/r4/lp-s/nwtsty"
    }
]